{
    "page": {
        "title": "Wir sind für Privatsphäre, Sicherheit und Transparenz im Internet",
        "description": "Wir sind eine Firma mit Fokus auf Privatsphäre, Transparenz und Sicherheit im Internet.",
        "privacy": "Datenschutz",
        "legal_notice": "Impressum",
        "licenses": "Lizensen",
        "contact": "Kontakt aufnehmen"
    },

    "header": {
        "home": "Startseite",
        "about": "Über uns",
        "projects": "Projekte",
        "contact": "Kontakt",
        "contact_us": "Kontaktiere uns"
    },

    "footer": {
        "build_with": "Entwickelt mit",
        "by_team_and": "vom Slynite Team und den",
        "contributers": "Contributern",
        "rights_reserved": "Alle Rechte vorbehalten."
    },

    "homepage": {
        "title": "Setze deine Privatsphäre, Transparenz und Sicherheit in den Vordergrund",
        "description": "Höre auch nach ausreden zu suchen, um deine Daten nicht zu schützen"
    },

    "test": {
        "helloworld": "Hallo Welt in Deutsch!"
    }
}